period_detection/__init__.py
period_detection/auxiliary_funcs.py
period_detection/find_period.py
period_detection/plot_funcs.py
period_detection-1.1.2.dist-info/LICENSE
period_detection-1.1.2.dist-info/METADATA
period_detection-1.1.2.dist-info/WHEEL
period_detection-1.1.2.dist-info/top_level.txt
period_detection-1.1.2.dist-info/RECORD
