Metadata-Version: 2.1
Name: period-detection
Version: 1.1.2
Author: Tim Breitenbach & Lauritz Rasbach
Author-email: tim.breitenbach@mathematik.uni-wuerzburg.de, rasbachlauritz@googlemail.com
Classifier: Programming Language :: Python :: 3
Classifier: License :: OSI Approved :: BSD License
Classifier: Operating System :: OS Independent
Requires-Python: >=3.6
License-File: LICENSE
Requires-Dist: numpy
Requires-Dist: scipy
Requires-Dist: pandas
Requires-Dist: scikit-learn
Requires-Dist: matplotlib
